neurotechdevkit/__init__.py
neurotechdevkit/grid.py
neurotechdevkit/imaging/__init__.py
neurotechdevkit/imaging/beamform.py
neurotechdevkit/imaging/demodulate.py
neurotechdevkit/imaging/util.py
neurotechdevkit/materials.py
neurotechdevkit/problem.py
neurotechdevkit/rendering/__init__.py
neurotechdevkit/rendering/_animations.py
neurotechdevkit/rendering/_formatting.py
neurotechdevkit/rendering/_source.py
neurotechdevkit/rendering/_target.py
neurotechdevkit/rendering/colormaps.py
neurotechdevkit/rendering/components/Angle=10°.png
neurotechdevkit/rendering/components/Angle=120°.png
neurotechdevkit/rendering/components/Angle=150°.png
neurotechdevkit/rendering/components/Angle=180°.png
neurotechdevkit/rendering/components/Angle=20°.png
neurotechdevkit/rendering/components/Angle=2°.png
neurotechdevkit/rendering/components/Angle=40°.png
neurotechdevkit/rendering/components/Angle=5°.png
neurotechdevkit/rendering/components/Angle=60°.png
neurotechdevkit/rendering/components/Angle=90°.png
neurotechdevkit/rendering/components/Angle=Flat.png
neurotechdevkit/rendering/components/target-dark.png
neurotechdevkit/rendering/components/target-light.png
neurotechdevkit/rendering/font.py
neurotechdevkit/rendering/fonts/Manrope-Bold.ttf
neurotechdevkit/rendering/fonts/Manrope-ExtraBold.ttf
neurotechdevkit/rendering/fonts/Manrope-ExtraLight.ttf
neurotechdevkit/rendering/fonts/Manrope-Light.ttf
neurotechdevkit/rendering/fonts/Manrope-Medium.ttf
neurotechdevkit/rendering/fonts/Manrope-Regular.ttf
neurotechdevkit/rendering/fonts/Manrope-SemiBold.ttf
neurotechdevkit/rendering/layers.py
neurotechdevkit/rendering/layout.py
neurotechdevkit/rendering/legends.py
neurotechdevkit/rendering/napari.py
neurotechdevkit/rendering/simulations.py
neurotechdevkit/results/__init__.py
neurotechdevkit/results/_metrics.py
neurotechdevkit/results/_results.py
neurotechdevkit/scenarios/__init__.py
neurotechdevkit/scenarios/_base.py
neurotechdevkit/scenarios/_resources.py
neurotechdevkit/scenarios/_shots.py
neurotechdevkit-0.6.11.dist-info/LICENSE
neurotechdevkit-0.6.11.dist-info/METADATA
neurotechdevkit-0.6.11.dist-info/WHEEL
neurotechdevkit-0.6.11.dist-info/RECORD
