Metadata-Version: 2.1
Name: neurotechdevkit
Version: 0.6.11
Summary: Neurotech Development Kit: an open-source software library designed to enhance accessibility to cutting-edge neurotechnology
License: Apache-2.0
Author: AE Studio
Author-email: bci@ae.studio
Maintainer: AE Studio
Maintainer-email: bci@ae.studio
Requires-Python: >=3.9,<3.12
Classifier: License :: OSI Approved :: Apache Software License
Classifier: Operating System :: MacOS
Classifier: Operating System :: Microsoft :: Windows
Classifier: Operating System :: POSIX :: Linux
Classifier: Programming Language :: Python :: 3
Classifier: Programming Language :: Python :: 3.9
Classifier: Programming Language :: Python :: 3.10
Classifier: Programming Language :: Python :: 3.11
Requires-Dist: devito (==4.7.1)
Requires-Dist: hdf5storage (>=0.1.18,<0.2.0)
Requires-Dist: imageio (>=2.21.2,<3.0.0)
Requires-Dist: ipywidgets
Requires-Dist: jupyter
Requires-Dist: jupyterlab (>=3.4.6,<4.0.0)
Requires-Dist: matplotlib (>=3.5.3,<4.0.0)
Requires-Dist: mkdocs-gallery (==0.7.6)
Requires-Dist: nest-asyncio (>=1.5.6,<2.0.0)
Requires-Dist: numpy (>=1.23.3,<2.0.0)
Requires-Dist: psutil (>=5.9.0,<6.0.0)
Requires-Dist: scipy (>=1.9.1,<2.0.0)
Requires-Dist: xarray (>=2022.3.0)
Project-URL: Bug Tracker, https://github.com/agencyenterprise/neurotechdevkit/issues
Project-URL: Documentation, https://agencyenterprise.github.io/neurotechdevkit/
Project-URL: Homepage, https://github.com/agencyenterprise/neurotechdevkit
